{
  "name": "Equestria Online Prologue",
  "description": "Adaptation of the Equestria Online prologue featuring James, David and early NPCs in a verbose screenplay format.",
  "version": "0.2.0",
  "style": "equestria-online",
  "characters": ["James", "David", "Honeycrisp", "Obsidian Stripe"],
  "locations": ["Barn Interior", "Forest Path", "Zebra's Hut Clearing"],
  "prompts": {
    "characters": ["characters/james.md", "characters/david.md", "characters/honeycrisp.md", "characters/obsidian-stripe.md"],
    "locations": ["locations/barn-interior.md", "locations/forest-path.md", "locations/zebra-hut.md"],
    "styles": ["styles/equestria-online.md"]
  }
}